rf_counterfactuals/__init__.py
rf_counterfactuals/costs_functions.py
rf_counterfactuals/metric_functions.py
rf_counterfactuals/rf_explainer.py
rf_counterfactuals/scores_functions.py
rf_counterfactuals/visualization.py
tests/__init__.py
tests/test_costs_functions.py
tests/test_everything.py
tests/test_rf_explainer.py
tests/test_scores_functions.py
rf_counterfactuals-0.1.0.dist-info/LICENSE
rf_counterfactuals-0.1.0.dist-info/METADATA
rf_counterfactuals-0.1.0.dist-info/WHEEL
rf_counterfactuals-0.1.0.dist-info/top_level.txt
rf_counterfactuals-0.1.0.dist-info/RECORD
