Metadata-Version: 2.1
Name: rf-counterfactuals
Version: 0.1.0
Summary: Random Forest counterfactual explanation
Home-page: https://github.com/Unn20/Random_Forest_Counterfactuals
Author: Maciej Leszczyk
Author-email: maciej.leszczyk98@email.com
License: CC 4.0
Keywords: counterfactual,explainable,xai,random forest
Requires-Python: >=3.8
License-File: LICENSE
Requires-Dist: numpy (>=1.23.1)
Requires-Dist: pandas (>=1.4.3)
Requires-Dist: scikit-learn (>=1.1.2)
Requires-Dist: scipy (>=1.9.0)
Requires-Dist: joblib (>=1.1.0)
